status_messenger/__init__.py
status_messenger/messenger.py
status_messenger-0.3.1.dist-info/licenses/LICENSE
status_messenger-0.3.1.dist-info/METADATA
status_messenger-0.3.1.dist-info/WHEEL
status_messenger-0.3.1.dist-info/top_level.txt
status_messenger-0.3.1.dist-info/RECORD
